{
    "id": 0,
    "mode": "CyberShake",
    "subtasks": [
        {
            "id": 0,
            "executionCost": 0,
            "memory": 0
        },
        {
            "id": 1,
            "executionCost": 3510,
            "memory": 56479
        },
        {
            "id": 2,
            "executionCost": 7150,
            "memory": 54963
        },
        {
            "id": 3,
            "executionCost": 9278,
            "memory": 36820
        },
        {
            "id": 4,
            "executionCost": 6374,
            "memory": 83164
        },
        {
            "id": 5,
            "executionCost": 5366,
            "memory": 94228
        },
        {
            "id": 6,
            "executionCost": 4113,
            "memory": 88649
        },
        {
            "id": 7,
            "executionCost": 5241,
            "memory": 90800
        },
        {
            "id": 8,
            "executionCost": 4569,
            "memory": 57658
        },
        {
            "id": 9,
            "executionCost": 7127,
            "memory": 63239
        },
        {
            "id": 10,
            "executionCost": 9710,
            "memory": 61642
        },
        {
            "id": 11,
            "executionCost": 4452,
            "memory": 72728
        },
        {
            "id": 12,
            "executionCost": 9458,
            "memory": 53396
        },
        {
            "id": 13,
            "executionCost": 2183,
            "memory": 98853
        },
        {
            "id": 14,
            "executionCost": 5145,
            "memory": 70901
        },
        {
            "id": 15,
            "executionCost": 6441,
            "memory": 84278
        },
        {
            "id": 16,
            "executionCost": 1987,
            "memory": 27783
        },
        {
            "id": 17,
            "executionCost": 5017,
            "memory": 33200
        },
        {
            "id": 18,
            "executionCost": 8716,
            "memory": 27665
        },
        {
            "id": 19,
            "executionCost": 9996,
            "memory": 63383
        },
        {
            "id": 20,
            "executionCost": 6718,
            "memory": 37921
        }
    ],
    "edges": [
        [
            0,
            19,
            693
        ],
        [
            0,
            2,
            924
        ],
        [
            0,
            1,
            253
        ],
        [
            1,
            3,
            403
        ],
        [
            1,
            4,
            808
        ],
        [
            1,
            5,
            811
        ],
        [
            1,
            6,
            300
        ],
        [
            2,
            7,
            855
        ],
        [
            2,
            8,
            842
        ],
        [
            2,
            9,
            802
        ],
        [
            2,
            10,
            363
        ],
        [
            3,
            11,
            180
        ],
        [
            3,
            12,
            612
        ],
        [
            3,
            13,
            850
        ],
        [
            3,
            14,
            741
        ],
        [
            3,
            15,
            994
        ],
        [
            3,
            16,
            491
        ],
        [
            3,
            17,
            125
        ],
        [
            3,
            18,
            202
        ],
        [
            4,
            11,
            676
        ],
        [
            4,
            12,
            350
        ],
        [
            4,
            13,
            204
        ],
        [
            4,
            14,
            139
        ],
        [
            4,
            15,
            464
        ],
        [
            4,
            16,
            707
        ],
        [
            4,
            17,
            313
        ],
        [
            4,
            18,
            315
        ],
        [
            5,
            11,
            834
        ],
        [
            5,
            12,
            851
        ],
        [
            5,
            13,
            805
        ],
        [
            5,
            14,
            460
        ],
        [
            5,
            15,
            631
        ],
        [
            5,
            16,
            283
        ],
        [
            5,
            17,
            888
        ],
        [
            5,
            18,
            927
        ],
        [
            6,
            11,
            486
        ],
        [
            6,
            12,
            448
        ],
        [
            6,
            13,
            613
        ],
        [
            6,
            14,
            355
        ],
        [
            6,
            15,
            244
        ],
        [
            6,
            16,
            851
        ],
        [
            6,
            17,
            896
        ],
        [
            6,
            18,
            318
        ],
        [
            7,
            11,
            781
        ],
        [
            7,
            12,
            213
        ],
        [
            7,
            13,
            806
        ],
        [
            7,
            14,
            660
        ],
        [
            7,
            15,
            851
        ],
        [
            7,
            16,
            601
        ],
        [
            7,
            17,
            232
        ],
        [
            7,
            18,
            672
        ],
        [
            8,
            11,
            958
        ],
        [
            8,
            12,
            981
        ],
        [
            8,
            13,
            187
        ],
        [
            8,
            14,
            859
        ],
        [
            8,
            15,
            277
        ],
        [
            8,
            16,
            808
        ],
        [
            8,
            17,
            593
        ],
        [
            8,
            18,
            285
        ],
        [
            9,
            11,
            489
        ],
        [
            9,
            12,
            184
        ],
        [
            9,
            13,
            118
        ],
        [
            9,
            14,
            209
        ],
        [
            9,
            15,
            942
        ],
        [
            9,
            16,
            481
        ],
        [
            9,
            17,
            462
        ],
        [
            9,
            18,
            651
        ],
        [
            10,
            11,
            130
        ],
        [
            10,
            12,
            358
        ],
        [
            10,
            13,
            545
        ],
        [
            10,
            14,
            241
        ],
        [
            10,
            15,
            989
        ],
        [
            10,
            16,
            632
        ],
        [
            10,
            17,
            353
        ],
        [
            10,
            18,
            713
        ],
        [
            11,
            20,
            872
        ],
        [
            12,
            20,
            393
        ],
        [
            13,
            20,
            243
        ],
        [
            14,
            20,
            907
        ],
        [
            15,
            20,
            794
        ],
        [
            16,
            20,
            416
        ],
        [
            17,
            20,
            720
        ],
        [
            18,
            20,
            648
        ]
    ],
    "deadline": 118576
}